{"Joey Gallo": {"2016-07-26": {"2B": "0", "BB": "0", "HR": "1", "IBB": "0", "BO": "6", "1B": "0", "3B": "0", "HBP": "0", "Opp": "OAK", "PA": "4", "AB": "4", "G": "1", "H": "1", "R": "1", "RBI": "1", "Team": "TEX", "CS": "0", "GDP": "0", "Pos": "1B", "SH": "0", "SO": "2", "SB": "0", "AVG": ".250", "SF": "0"}, "2016-09-07": {"2B": "0", "BB": "0", "HR": "0", "IBB": "0", "BO": "8", "1B": "0", "3B": "0", "HBP": "0", "Opp": "@SEA", "PA": "1", "AB": "1", "G": "1", "H": "0", "R": "0", "RBI": "0", "Team": "TEX", "CS": "0", "GDP": "0", "Pos": "PH", "SH": "0", "SO": "1", "SB": "0", "AVG": ".000", "SF": "0"}, "2016-07-28": {"2B": "0", "BB": "0", "HR": "0", "IBB": "0", "BO": "6", "1B": "0", "3B": "0", "HBP": "0", "Opp": "KCR", "PA": "3", "AB": "3", "G": "1", "H": "0", "R": "0", "RBI": "0", "Team": "TEX", "CS": "0", "GDP": "0", "Pos": "DH", "SH": "0", "SO": "2", "SB": "0", "AVG": ".000", "SF": "0"}, "2016-07-29": {"2B": "0", "BB": "1", "HR": "0", "IBB": "0", "BO": "8", "1B": "0", "3B": "0", "HBP": "0", "Opp": "KCR", "PA": "4", "AB": "3", "G": "1", "H": "0", "R": "0", "RBI": "0", "Team": "TEX", "CS": "0", "GDP": "0", "Pos": "DH", "SH": "0", "SO": "2", "SB": "0", "AVG": ".000", "SF": "0"}, "2016-09-13": {"2B": "0", "BB": "0", "HR": "0", "IBB": "0", "BO": "9", "1B": "0", "3B": "0", "HBP": "0", "Opp": "@HOU", "PA": "1", "AB": "1", "G": "1", "H": "0", "R": "0", "RBI": "0", "Team": "TEX", "CS": "0", "GDP": "0", "Pos": "PH", "SH": "0", "SO": "1", "SB": "0", "AVG": ".000", "SF": "0"}, "2016-09-11": {"2B": "0", "BB": "1", "HR": "0", "IBB": "0", "BO": "8", "1B": "0", "3B": "0", "HBP": "0", "Opp": "@LAA", "PA": "1", "AB": "0", "G": "1", "H": "0", "R": "0", "RBI": "0", "Team": "TEX", "CS": "0", "GDP": "0", "Pos": "PH-3B", "SH": "0", "SO": "0", "SB": "0", "AVG": ".000", "SF": "0"}, "2016-09-10": {"2B": "0", "BB": "0", "HR": "0", "IBB": "0", "BO": "3", "1B": "0", "3B": "0", "HBP": "0", "Opp": "@LAA", "PA": "0", "AB": "0", "G": "1", "H": "0", "R": "0", "RBI": "0", "Team": "TEX", "CS": "0", "GDP": "0", "Pos": "PR-DH", "SH": "0", "SO": "0", "SB": "0", "AVG": ".000", "SF": "0"}, "2016-05-23": {"2B": "0", "BB": "0", "HR": "0", "IBB": "0", "BO": "8", "1B": "0", "3B": "0", "HBP": "0", "Opp": "LAA", "PA": "1", "AB": "1", "G": "1", "H": "0", "R": "0", "RBI": "0", "Team": "TEX", "CS": "0", "GDP": "0", "Pos": "PH", "SH": "0", "SO": "0", "SB": "0", "AVG": ".000", "SF": "0"}, "2016-07-30": {"2B": "0", "BB": "0", "HR": "0", "IBB": "0", "BO": "8", "1B": "0", "3B": "0", "HBP": "0", "Opp": "KCR", "PA": "3", "AB": "3", "G": "1", "H": "0", "R": "0", "RBI": "0", "Team": "TEX", "CS": "0", "GDP": "0", "Pos": "DH", "SH": "0", "SO": "3", "SB": "0", "AVG": ".000", "SF": "0"}, "2016-07-27": {"2B": "0", "BB": "0", "HR": "0", "IBB": "0", "BO": "9", "1B": "0", "3B": "0", "HBP": "0", "Opp": "OAK", "PA": "1", "AB": "1", "G": "1", "H": "0", "R": "0", "RBI": "0", "Team": "TEX", "CS": "0", "GDP": "0", "Pos": "PH", "SH": "0", "SO": "0", "SB": "0", "AVG": ".000", "SF": "0"}}}